llamore/__init__.py
llamore/extractors.py
llamore/metrics.py
llamore/parser.py
llamore/prompter.py
llamore/reference.py
llamore-0.2.0.dist-info/METADATA
llamore-0.2.0.dist-info/WHEEL
llamore-0.2.0.dist-info/top_level.txt
llamore-0.2.0.dist-info/RECORD
