Metadata-Version: 2.4
Name: Llamore
Version: 0.2.0
Summary: Large LAnguage MOdels for Reference Extraction: extract and evaluate references from free-form text using LLM/VLMs.
Author-email: David Carreto Fidalgo <david.carreto.fidalgo@mpcdf.mpg.de>, Christian Boulanger <boulanger@lhlt.mpg.de>, Andreas Wagner <wagner@lhlt.mpg.de>
Project-URL: Repository, https://github.com/mpilhlt/llamore
Requires-Python: >=3.10
Requires-Dist: google-genai>=1.8.0
Requires-Dist: lxml>=5.3.1
Requires-Dist: numpy>=2.2.3
Requires-Dist: openai>=1.68.2
Requires-Dist: pydantic>=2.10.6
Requires-Dist: pymupdf>=1.25.4
Requires-Dist: rapidfuzz>=3.12.2
Requires-Dist: rich>=13.9.4
Requires-Dist: scipy>=1.15.2
